layerlearn/__init__.py
layerlearn/baseAdaC.py
layerlearn/baseAdaR.py
layerlearn/baseCatC.py
layerlearn/baseCatR.py
layerlearn/baseDecisionC.py
layerlearn/baseDecisionR.py
layerlearn/baseForestC.py
layerlearn/baseForestR.py
layerlearn/baseGradientC.py
layerlearn/baseGradientR.py
layerlearn/baseKNNC.py
layerlearn/baseKNNR.py
layerlearn/baseLightC.py
layerlearn/baseLightR.py
layerlearn/baseLinear.py
layerlearn/baseLogistic.py
layerlearn/baseSupportC.py
layerlearn/baseSupportR.py
layerlearn/baseXGBC.py
layerlearn/baseXGBR.py
layerlearn/flexiblestacked.py
layeredlearning-1.6.7.dist-info/METADATA
layeredlearning-1.6.7.dist-info/WHEEL
layeredlearning-1.6.7.dist-info/licenses/LICENSE
layeredlearning-1.6.7.dist-info/RECORD
