Metadata-Version: 2.4
Name: layeredlearning
Version: 1.6.7
Summary: A library for Augmented Model Stacking and ensemble with a focus on flexibility and performance.
Project-URL: Homepage, https://github.com/Mr-J12/newalgo
Author-email: Yashwant Singh Rawat <yashwantsinghrawat696@gmail.com>
License: MIT License
License-File: LICENSE
Classifier: Intended Audience :: Developers
Classifier: Operating System :: OS Independent
Classifier: Programming Language :: Python :: 3
Classifier: Topic :: Scientific/Engineering :: Artificial Intelligence
Requires-Python: >=3.8
Requires-Dist: catboost>=1.2.2
Requires-Dist: lightgbm>=3.3.5
Requires-Dist: numpy>=1.20.0
Requires-Dist: scikit-learn>=1.0.0
Requires-Dist: xgboost>=1.7.0
